aiohttp_proxy/__init__.py
aiohttp_proxy/connector.py
aiohttp_proxy/errors.py
aiohttp_proxy/helpers.py
aiohttp_proxy/proto.py
aiohttp_proxy-0.1.2.dist-info/LICENSE.txt
aiohttp_proxy-0.1.2.dist-info/METADATA
aiohttp_proxy-0.1.2.dist-info/WHEEL
aiohttp_proxy-0.1.2.dist-info/top_level.txt
aiohttp_proxy-0.1.2.dist-info/RECORD
