Metadata-Version: 2.1
Name: aiohttp_proxy
Version: 0.1.2
Summary: Full-featured proxy connector for aiohttp
Home-page: https://github.com/Skactor/aiohttp-proxy
Author: Skactor
Author-email: sk4ct0r@gmail.com
License: Apache 2
Keywords: asyncio aiohttp socks socks5 socks4 http https proxy
Platform: UNKNOWN
